{
    "SHD": [
        {"x1": 9, "y1": 270, "x2": 62, "y2": 327}
    ],
    "D": [
        {"x1": 16, "y1": 4, "x2": 63, "y2": 59},
        {"x1": 20, "y1": 68, "x2": 68, "y2": 126},
        {"x1": 18, "y1": 137, "x2": 67, "y2": 193},
        {"x1": 16, "y1": 203, "x2": 64, "y2": 261}
    ],
    "U": [
        {"x1": 427, "y1": 5, "x2": 476, "y2": 60},
        {"x1": 432, "y1": 70, "x2": 480, "y2": 127},
        {"x1": 432, "y1": 139, "x2": 481, "y2": 194},
        {"x1": 428, "y1": 204, "x2": 476, "y2": 261}
    ],
    "L": [
        {"x1": 223, "y1": 4, "x2": 268, "y2": 59},
        {"x1": 238, "y1": 70, "x2": 261, "y2": 126},
        {"x1": 227, "y1": 138, "x2": 270, "y2": 193},
        {"x1": 235, "y1": 204, "x2": 257, "y2": 260}
    ],
    "DL": [
        {"x1": 113, "y1": 3, "x2": 173, "y2": 61},
        {"x1": 125, "y1": 68, "x2": 169, "y2": 128},
        {"x1": 124, "y1": 136, "x2": 169, "y2": 195},
        {"x1": 121, "y1": 203, "x2": 165, "y2": 262}
    ],
    "UL": [
        {"x1": 323, "y1": 3, "x2": 375, "y2": 62},
        {"x1": 334, "y1": 68, "x2": 371, "y2": 129},
        {"x1": 327, "y1": 136, "x2": 381, "y2": 196},
        {"x1": 332, "y1": 202, "x2": 366, "y2": 263}
    ],
    "R": [
        {"x1": 223, "y1": 4, "x2": 268, "y2": 59},
        {"x1": 238, "y1": 70, "x2": 261, "y2": 126},
        {"x1": 227, "y1": 138, "x2": 270, "y2": 193},
        {"x1": 235, "y1": 204, "x2": 257, "y2": 260}
    ],
    "DR": [
        {"x1": 113, "y1": 3, "x2": 173, "y2": 61},
        {"x1": 125, "y1": 68, "x2": 169, "y2": 128},
        {"x1": 124, "y1": 136, "x2": 169, "y2": 195},
        {"x1": 121, "y1": 203, "x2": 165, "y2": 262}
    ],
    "UR": [
        {"x1": 323, "y1": 3, "x2": 375, "y2": 62},
        {"x1": 334, "y1": 68, "x2": 371, "y2": 129},
        {"x1": 327, "y1": 136, "x2": 381, "y2": 196},
        {"x1": 332, "y1": 202, "x2": 366, "y2": 263}
    ]
}